linthell/__init__.py
linthell/__main__.py
linthell/cli.py
linthell/commands/__init__.py
linthell/commands/baseline.py
linthell/commands/lint.py
linthell/commands/pre_commit/__init__.py
linthell/commands/pre_commit/baseline.py
linthell/commands/pre_commit/cli.py
linthell/commands/pre_commit/lint.py
linthell/plugins/__init__.py
linthell/plugins/base.py
linthell/plugins/black_check.py
linthell/plugins/black_diff.py
linthell/plugins/flake8.py
linthell/plugins/isort_diff.py
linthell/plugins/mypy.py
linthell/plugins/pydocstyle.py
linthell/plugins/pylint.py
linthell/plugins/regex.py
linthell/utils/__init__.py
linthell/utils/baseline.py
linthell/utils/click.py
linthell/utils/config.py
linthell/utils/id_lines.py
linthell/utils/lint.py
linthell/utils/linters.py
linthell/utils/path.py
linthell/utils/pre_commit.py
linthell/utils/types.py
linthell-1.3.0.dist-info/METADATA
linthell-1.3.0.dist-info/WHEEL
linthell-1.3.0.dist-info/entry_points.txt
linthell-1.3.0.dist-info/RECORD
