Metadata-Version: 2.1
Name: linthell
Version: 1.3.0
Summary: Universal flakehell replacement for almost any linter you like
Home-page: https://github.com/discrimy/linthell
Author: Alexander Bespalov
Author-email: discrimy.off@gmail.com
Requires-Python: >=3.7,<4.0
Classifier: Programming Language :: Python :: 3
Classifier: Programming Language :: Python :: 3.7
Classifier: Programming Language :: Python :: 3.8
Classifier: Programming Language :: Python :: 3.9
Classifier: Programming Language :: Python :: 3.10
Classifier: Programming Language :: Python :: 3.11
Requires-Dist: click (>=8.1.3,<9.0.0)
Requires-Dist: importlib-metadata ; python_version < "3.10"
Requires-Dist: typing-extensions (>=4.4.0,<5.0.0)
Project-URL: Repository, https://github.com/discrimy/linthell
